catflow_validate/__init__.py
catflow_validate/__version__.py
catflow_validate/cli.py
catflow_validate/format.py
catflow_validate/landuse.py
catflow_validate/report.py
catflow_validate/soil.py
catflow_validate/testing/__init__.py
catflow_validate/testing/test_input_files.py
catflow_validate-0.7.1.dist-info/LICENSE
catflow_validate-0.7.1.dist-info/METADATA
catflow_validate-0.7.1.dist-info/WHEEL
catflow_validate-0.7.1.dist-info/entry_points.txt
catflow_validate-0.7.1.dist-info/top_level.txt
catflow_validate-0.7.1.dist-info/RECORD
