Metadata-Version: 2.1
Name: catflow-validate
Version: 0.7.1
Author: Mirko Mälicke
Author-email: mirko.maelicke@kit.edu
License-File: LICENSE
Requires-Dist: Click
Requires-Dist: pytest
Requires-Dist: tabulate
